<?xml version="1.0" encoding="UTF-8"?>
<RetrieveValueSetResponse xmlns="urn:ihe:iti:svs:2008"
                          xmlns:xsi="http://www.w3.org/2001/XMLSchema-instance">
   <ValueSet dateFin=""
             dateMaj="20251024164038"
             dateValid=""
             description="Traduction Française"
             displayName="TimingEventSupplementFr"
             id=""
             typeFichier="TRE"
             urlFichier="">
      <ConceptList>
         <Concept code="AC"
                  codeSystem=""
                  dateFin=""
                  dateMaj=""
                  dateValid=""
                  displayName=""
                  longDesignation=""
                  shortDesignation="Avant le repas"
                  descriptionMetier=""/>
         <Concept code="ACD"
                  codeSystem=""
                  dateFin=""
                  dateMaj=""
                  dateValid=""
                  displayName=""
                  longDesignation=""
                  shortDesignation="Avant le déjeuner"
                  descriptionMetier=""/>
         <Concept code="ACM"
                  codeSystem=""
                  dateFin=""
                  dateMaj=""
                  dateValid=""
                  displayName=""
                  longDesignation=""
                  shortDesignation="Avant le petit-déjeuner"
                  descriptionMetier=""/>
         <Concept code="ACV"
                  codeSystem=""
                  dateFin=""
                  dateMaj=""
                  dateValid=""
                  displayName=""
                  longDesignation=""
                  shortDesignation="Avant le dîner"
                  descriptionMetier=""/>
         <Concept code="C"
                  codeSystem=""
                  dateFin=""
                  dateMaj=""
                  dateValid=""
                  displayName=""
                  longDesignation=""
                  shortDesignation="Pendant les repas"
                  descriptionMetier=""/>
         <Concept code="CD"
                  codeSystem=""
                  dateFin=""
                  dateMaj=""
                  dateValid=""
                  displayName=""
                  longDesignation=""
                  shortDesignation="Pendant le déjeuner"
                  descriptionMetier=""/>
         <Concept code="CM"
                  codeSystem=""
                  dateFin=""
                  dateMaj=""
                  dateValid=""
                  displayName=""
                  longDesignation=""
                  shortDesignation="Pendant le petit-déjeuner"
                  descriptionMetier=""/>
         <Concept code="CV"
                  codeSystem=""
                  dateFin=""
                  dateMaj=""
                  dateValid=""
                  displayName=""
                  longDesignation=""
                  shortDesignation="Pendant le dîner"
                  descriptionMetier=""/>
         <Concept code="HS"
                  codeSystem=""
                  dateFin=""
                  dateMaj=""
                  dateValid=""
                  displayName=""
                  longDesignation=""
                  shortDesignation="Au coucher"
                  descriptionMetier=""/>
         <Concept code="IC"
                  codeSystem=""
                  dateFin=""
                  dateMaj=""
                  dateValid=""
                  displayName=""
                  longDesignation=""
                  shortDesignation="Entre les repas"
                  descriptionMetier=""/>
         <Concept code="ICD"
                  codeSystem=""
                  dateFin=""
                  dateMaj=""
                  dateValid=""
                  displayName=""
                  longDesignation=""
                  shortDesignation="Entre le déjeuner et le dîner"
                  descriptionMetier=""/>
         <Concept code="ICM"
                  codeSystem=""
                  dateFin=""
                  dateMaj=""
                  dateValid=""
                  displayName=""
                  longDesignation="Entre le petit-déjeûner et le déjeûner"
                  shortDesignation=""
                  descriptionMetier=""/>
         <Concept code="ICV"
                  codeSystem=""
                  dateFin=""
                  dateMaj=""
                  dateValid=""
                  displayName=""
                  longDesignation=""
                  shortDesignation="Entre le diner et le coucher"
                  descriptionMetier=""/>
         <Concept code="PC"
                  codeSystem=""
                  dateFin=""
                  dateMaj=""
                  dateValid=""
                  displayName=""
                  longDesignation=""
                  shortDesignation="Après le repas"
                  descriptionMetier=""/>
         <Concept code="PCD"
                  codeSystem=""
                  dateFin=""
                  dateMaj=""
                  dateValid=""
                  displayName=""
                  longDesignation=""
                  shortDesignation="Après le déjeuner"
                  descriptionMetier=""/>
         <Concept code="PCM"
                  codeSystem=""
                  dateFin=""
                  dateMaj=""
                  dateValid=""
                  displayName=""
                  longDesignation=""
                  shortDesignation="Après le petit-déjeuner"
                  descriptionMetier=""/>
         <Concept code="PCV"
                  codeSystem=""
                  dateFin=""
                  dateMaj=""
                  dateValid=""
                  displayName=""
                  longDesignation=""
                  shortDesignation="Après le dîner"
                  descriptionMetier=""/>
         <Concept code="WAKE"
                  codeSystem=""
                  dateFin=""
                  dateMaj=""
                  dateValid=""
                  displayName=""
                  longDesignation=""
                  shortDesignation="Au réveil"
                  descriptionMetier=""/>
      </ConceptList>
   </ValueSet>
</RetrieveValueSetResponse>
