{
  "resourceType" : "ValueSet",
  "id" : "27994b57-dc94-4757-8dac-7e080c7b4eb5-2874",
  "url" : "http://hl7.org/fhir/comparison/ValueSet/27994b57-dc94-4757-8dac-7e080c7b4eb5-2874",
  "name" : "IntersectionJdvTypeServiceCisisAndJdvTypeServiceCisis",
  "title" : "Intersection of JDV Type Service CISIS And JDV Type Service CISIS",
  "status" : "active",
  "date" : "2025-07-01T15:53:59+00:00",
  "jurisdiction" : [{
    "coding" : [{
      "system" : "urn:iso:std:iso:3166",
      "code" : "FR"
    }]
  }],
  "compose" : {
    "include" : [{
      "concept" : [{
        "code" : "ORG-141",
        "display" : "Unité Kangourou"
      },
      {
        "code" : "GEN-092.06.05",
        "display" : "Autre type de service"
      }]
    },
    {
      "concept" : [{
        "code" : "309904001",
        "display" : "unité de soins intensifs"
      },
      {
        "code" : "1279968000",
        "display" : "service de néonatalogie"
      },
      {
        "code" : "405269005",
        "display" : "unité de soins intensifs néonatals"
      }]
    }]
  }
}