{
  "resourceType" : "ValueSet",
  "id" : "jdv-hl7-v3-PersonalRelationshipRoleType-cisis",
  "meta" : {
    "versionId" : "9",
    "lastUpdated" : "2026-04-20T16:59:39.116+02:00",
    "profile" : ["http://hl7.org/fhir/StructureDefinition/shareablevalueset"]
  },
  "language" : "fr-FR",
  "text" : {
    "status" : "generated",
    "div" : "<div xml:lang=\"fr-FR\" xmlns=\"http://www.w3.org/1999/xhtml\" lang=\"fr-FR\"><p class=\"res-header-id\"><b>Narratif généré : EnsembleValeurs jdv-hl7-v3-PersonalRelationshipRoleType-cisis</b></p><a name=\"jdv-hl7-v3-PersonalRelationshipRoleType-cisis\"> </a><a name=\"hcjdv-hl7-v3-PersonalRelationshipRoleType-cisis\"> </a><div style=\"display: inline-block; background-color: #d9e0e7; padding: 6px; margin: 4px; border: 1px solid #8da1b4; border-radius: 5px; line-height: 60%\"><p style=\"margin-bottom: 0px\">version : 9; Dernière mise à jour : 2026-04-20 16:59:39+0200; Langue : fr-FR</p><p style=\"margin-bottom: 0px\">Profil: <a href=\"http://hl7.org/fhir/R4/shareablevalueset.html\">Shareable ValueSet</a></p></div><ul><li>Include ce(s) code(s) tel qu'il(s) est (sont) défini(s) dans <code>http://terminology.hl7.org/CodeSystem/v3-RoleCode</code><span title=\"La version est explicitement indiquée comme étant 2018-08-12\"> version &#x1F4CD;2018-08-12</span><table class=\"none\"><tr><td style=\"white-space:nowrap\"><b>Code</b></td><td><b>Affichage</b></td></tr><tr><td>ADOPTF</td><td>Père adoptif</td></tr><tr><td>ADOPTM</td><td>Mère adoptive</td></tr><tr><td>ADOPTP</td><td>Parent adoptif, au sens père ou mère</td></tr><tr><td>AUNT</td><td>Tante</td></tr><tr><td>BRO</td><td>Frère</td></tr><tr><td>BROINLAW</td><td>Beau-frère</td></tr><tr><td>CHILD</td><td>Enfant</td></tr><tr><td>CHLDADOPT</td><td>Enfant adopté</td></tr><tr><td>CHLDFOST</td><td>Enfant placé en famille d'accueil</td></tr><tr><td>CHLDINLAW</td><td>Gendre ou belle-fille</td></tr><tr><td>COUSN</td><td>Cousin(e)</td></tr><tr><td>DAU</td><td>Fille biologique</td></tr><tr><td>DAUADOPT</td><td>Fille adoptive</td></tr><tr><td>DAUC</td><td>Fille</td></tr><tr><td>DAUFOST</td><td>Fille placée en famille d'accueil</td></tr><tr><td>DAUINLAW</td><td>Belle-fille</td></tr><tr><td>DOMPART</td><td>Concubin(e) ou partenaire PACS</td></tr><tr><td>EXT</td><td>Autre membre de la famille sans lien génétique direct</td></tr><tr><td>FAMMEMB</td><td>Autre membre de la famille</td></tr><tr><td>FMRSPS</td><td>Ancien époux ou ancienne épouse</td></tr><tr><td>FRND</td><td>Autre proche</td></tr><tr><td>FTH</td><td>Père</td></tr><tr><td>FTHFOST</td><td>Assistant familial - Famille d'accueil</td></tr><tr><td>FTHINLAW</td><td>Beau-père</td></tr><tr><td>FTWIN</td><td>Jumeau ou jumelle dizygote</td></tr><tr><td>FTWINBRO</td><td>Jumeau dizygote</td></tr><tr><td>FTWINSIS</td><td>Jumelle dizygote</td></tr><tr><td>GESTM</td><td>Mère porteuse</td></tr><tr><td>GGRFTH</td><td>Arrière-grand-père</td></tr><tr><td>GGRMTH</td><td>Arrière-grand-mère</td></tr><tr><td>GGRPRN</td><td>Arrière-grand-parent</td></tr><tr><td>GRFTH</td><td>Grand-père</td></tr><tr><td>GRMTH</td><td>Grand-mère</td></tr><tr><td>GRPRN</td><td>Grand-parent</td></tr><tr><td>GRNDCHILD</td><td>Petit-enfant</td></tr><tr><td>GRNDDAU</td><td>Petite-fille</td></tr><tr><td>GRNDSON</td><td>Petit-fils</td></tr><tr><td>HBRO</td><td>Demi-frère</td></tr><tr><td>HSIB</td><td>Demi-frère ou demi-sœur</td></tr><tr><td>HSIS</td><td>Demi-sœur</td></tr><tr><td>HUSB</td><td>Epoux</td></tr><tr><td>ITWIN</td><td>Jumeau ou jumelle monozygote</td></tr><tr><td>ITWINBRO</td><td>Jumeau monozygote</td></tr><tr><td>ITWINSIS</td><td>Jumelle monozygote</td></tr><tr><td>MAUNT</td><td>Tante maternelle</td></tr><tr><td>MCOUSN</td><td>Cousin (maternel)</td></tr><tr><td>MGGRFTH</td><td>Arrière-grand-père maternel</td></tr><tr><td>MGGRMTH</td><td>Arrière-grand-mère maternelle</td></tr><tr><td>MGGRPRN</td><td>Arrière grand parent maternel</td></tr><tr><td>MGRFTH</td><td>Grand-père maternel</td></tr><tr><td>MGRMTH</td><td>Grand-mère maternelle</td></tr><tr><td>MGRPRN</td><td>Grand parent maternel</td></tr><tr><td>MTH</td><td>Mère</td></tr><tr><td>MTHFOST</td><td>Assistante familiale - Famille d'accueil</td></tr><tr><td>MTHINLAW</td><td>Belle-mère</td></tr><tr><td>MUNCLE</td><td>Oncle maternel</td></tr><tr><td>NBOR</td><td>Voisin(e)</td></tr><tr><td>NBRO</td><td>Frère biologique</td></tr><tr><td>NCHILD</td><td>Enfant biologique</td></tr><tr><td>NEPHEW</td><td>Neveu</td></tr><tr><td>NFTH</td><td>Père biologique</td></tr><tr><td>NFTHF</td><td>Père biologique du fœtus</td></tr><tr><td>NIECE</td><td>Nièce</td></tr><tr><td>NIENEPH</td><td>Neveu ou nièce</td></tr><tr><td>NMTH</td><td>Mère biologique</td></tr><tr><td>NMTHF</td><td>Mère biologique du fœtus</td></tr><tr><td>NPRN</td><td>Parent biologique, au sens père ou mère</td></tr><tr><td>NSIB</td><td>Frère ou soeur biologique</td></tr><tr><td>NSIS</td><td>Soeur biologique</td></tr><tr><td>PAUNT</td><td>Tante paternelle</td></tr><tr><td>PCOUSN</td><td>Cousin (paternel)</td></tr><tr><td>PGGRFTH</td><td>Arrière-grand-père paternel</td></tr><tr><td>PGGRMTH</td><td>Arrière-grand-mère paternelle</td></tr><tr><td>PGGRPRN</td><td>Arrière grand parent paternel</td></tr><tr><td>PGRFTH</td><td>Grand-père paternel</td></tr><tr><td>PGRMTH</td><td>Grand-mère paternelle</td></tr><tr><td>PGRPRN</td><td>Grand parent paternel</td></tr><tr><td>PRN</td><td>Parent, au sens père ou mère</td></tr><tr><td>PRNINLAW</td><td>Beau-père ou belle-mère</td></tr><tr><td>PRNFOST</td><td>Parent, au sens famille d'accueil</td></tr><tr><td>PUNCLE</td><td>Oncle paternel</td></tr><tr><td>RESPRSN</td><td>Responsable légal</td></tr><tr><td>ROOM</td><td>Personne vivant sous le même toit</td></tr><tr><td>SIB</td><td>Frère ou sœur</td></tr><tr><td>SIBINLAW</td><td>Beau-frère ou belle-sœur</td></tr><tr><td>SIGOTHR</td><td>Conjoint</td></tr><tr><td>SIS</td><td>Sœur</td></tr><tr><td>SISINLAW</td><td>Belle-sœur</td></tr><tr><td>SON</td><td>Fils biologique</td></tr><tr><td>SONADOPT</td><td>Fils adoptif</td></tr><tr><td>SONC</td><td>Fils</td></tr><tr><td>SONFOST</td><td>Garçon placé en famille d'accueil</td></tr><tr><td>SONINLAW</td><td>Gendre</td></tr><tr><td>SPS</td><td>Epoux ou épouse</td></tr><tr><td>STPBRO</td><td>Fils du beau-père ou de la belle-mère</td></tr><tr><td>STPFTH</td><td>Beau-père - époux du père ou de la mère</td></tr><tr><td>STPMTH</td><td>Belle-mère - épouse du père ou de la mère</td></tr><tr><td>STPCHLD</td><td>Enfant du conjoint, issu d'un mariage précédent</td></tr><tr><td>STPDAU</td><td>Fille du conjoint, issue d'un mariage précédent</td></tr><tr><td>STPPRN</td><td>Beau-père ou belle-mère - époux(se) du père ou de la mère</td></tr><tr><td>STPSIB</td><td>Enfant du beau-père ou de la belle-mère</td></tr><tr><td>STPSIS</td><td>Fille du beau-père ou de la belle-mère</td></tr><tr><td>STPSON</td><td>Fils du conjoint, issu d'un mariage précédent</td></tr><tr><td>TWIN</td><td>Frère jumeau ou soeur jumelle</td></tr><tr><td>TWINBRO</td><td>Frère jumeau</td></tr><tr><td>TWINSIS</td><td>Soeur jumelle</td></tr><tr><td>UNCLE</td><td>Oncle</td></tr><tr><td>WIFE</td><td>Epouse</td></tr></table></li></ul></div>"
  },
  "extension" : [{
    "url" : "http://hl7.org/fhir/StructureDefinition/resource-effectivePeriod",
    "valuePeriod" : {
      "start" : "2010-01-01T00:00:00+01:00"
    }
  }],
  "url" : "https://smt.esante.gouv.fr/fhir/ValueSet/jdv-hl7-v3-PersonalRelationshipRoleType-cisis",
  "identifier" : [{
    "system" : "urn:ietf:rfc:3986",
    "value" : "urn:oid:2.16.840.1.113883.1.11.19563"
  }],
  "version" : "20260420150249",
  "name" : "PersonalRelationshipRoleType",
  "title" : "PersonalRelationshipRoleType",
  "status" : "active",
  "experimental" : false,
  "date" : "2026-04-20T15:02:49+01:00",
  "publisher" : "Agence du Numérique en Santé(ANS) -2 - 10 Rue d'Oradour-sur-Glane, 75015 Paris",
  "description" : "PersonalRelationshipRoleType",
  "jurisdiction" : [{
    "coding" : [{
      "system" : "urn:iso:std:iso:3166",
      "code" : "FRA"
    }]
  }],
  "compose" : {
    "include" : [{
      "system" : "http://terminology.hl7.org/CodeSystem/v3-RoleCode",
      "version" : "2018-08-12",
      "concept" : [{
        "code" : "ADOPTF",
        "display" : "Père adoptif"
      },
      {
        "code" : "ADOPTM",
        "display" : "Mère adoptive"
      },
      {
        "code" : "ADOPTP",
        "display" : "Parent adoptif, au sens père ou mère"
      },
      {
        "code" : "AUNT",
        "display" : "Tante"
      },
      {
        "code" : "BRO",
        "display" : "Frère"
      },
      {
        "code" : "BROINLAW",
        "display" : "Beau-frère"
      },
      {
        "code" : "CHILD",
        "display" : "Enfant"
      },
      {
        "code" : "CHLDADOPT",
        "display" : "Enfant adopté"
      },
      {
        "code" : "CHLDFOST",
        "display" : "Enfant placé en famille d'accueil"
      },
      {
        "code" : "CHLDINLAW",
        "display" : "Gendre ou belle-fille"
      },
      {
        "code" : "COUSN",
        "display" : "Cousin(e)"
      },
      {
        "code" : "DAU",
        "display" : "Fille biologique"
      },
      {
        "code" : "DAUADOPT",
        "display" : "Fille adoptive"
      },
      {
        "code" : "DAUC",
        "display" : "Fille"
      },
      {
        "code" : "DAUFOST",
        "display" : "Fille placée en famille d'accueil"
      },
      {
        "code" : "DAUINLAW",
        "display" : "Belle-fille"
      },
      {
        "code" : "DOMPART",
        "display" : "Concubin(e) ou partenaire PACS"
      },
      {
        "code" : "EXT",
        "display" : "Autre membre de la famille sans lien génétique direct"
      },
      {
        "code" : "FAMMEMB",
        "display" : "Autre membre de la famille"
      },
      {
        "code" : "FMRSPS",
        "display" : "Ancien époux ou ancienne épouse"
      },
      {
        "code" : "FRND",
        "display" : "Autre proche"
      },
      {
        "code" : "FTH",
        "display" : "Père"
      },
      {
        "code" : "FTHFOST",
        "display" : "Assistant familial - Famille d'accueil"
      },
      {
        "code" : "FTHINLAW",
        "display" : "Beau-père"
      },
      {
        "code" : "FTWIN",
        "display" : "Jumeau ou jumelle dizygote"
      },
      {
        "code" : "FTWINBRO",
        "display" : "Jumeau dizygote"
      },
      {
        "code" : "FTWINSIS",
        "display" : "Jumelle dizygote"
      },
      {
        "code" : "GESTM",
        "display" : "Mère porteuse"
      },
      {
        "code" : "GGRFTH",
        "display" : "Arrière-grand-père"
      },
      {
        "code" : "GGRMTH",
        "display" : "Arrière-grand-mère"
      },
      {
        "code" : "GGRPRN",
        "display" : "Arrière-grand-parent"
      },
      {
        "code" : "GRFTH",
        "display" : "Grand-père"
      },
      {
        "code" : "GRMTH",
        "display" : "Grand-mère"
      },
      {
        "code" : "GRPRN",
        "display" : "Grand-parent"
      },
      {
        "code" : "GRNDCHILD",
        "display" : "Petit-enfant"
      },
      {
        "code" : "GRNDDAU",
        "display" : "Petite-fille"
      },
      {
        "code" : "GRNDSON",
        "display" : "Petit-fils"
      },
      {
        "code" : "HBRO",
        "display" : "Demi-frère"
      },
      {
        "code" : "HSIB",
        "display" : "Demi-frère ou demi-sœur"
      },
      {
        "code" : "HSIS",
        "display" : "Demi-sœur"
      },
      {
        "code" : "HUSB",
        "display" : "Epoux"
      },
      {
        "code" : "ITWIN",
        "display" : "Jumeau ou jumelle monozygote"
      },
      {
        "code" : "ITWINBRO",
        "display" : "Jumeau monozygote"
      },
      {
        "code" : "ITWINSIS",
        "display" : "Jumelle monozygote"
      },
      {
        "code" : "MAUNT",
        "display" : "Tante maternelle"
      },
      {
        "code" : "MCOUSN",
        "display" : "Cousin (maternel)"
      },
      {
        "code" : "MGGRFTH",
        "display" : "Arrière-grand-père maternel"
      },
      {
        "code" : "MGGRMTH",
        "display" : "Arrière-grand-mère maternelle"
      },
      {
        "code" : "MGGRPRN",
        "display" : "Arrière grand parent maternel"
      },
      {
        "code" : "MGRFTH",
        "display" : "Grand-père maternel"
      },
      {
        "code" : "MGRMTH",
        "display" : "Grand-mère maternelle"
      },
      {
        "code" : "MGRPRN",
        "display" : "Grand parent maternel"
      },
      {
        "code" : "MTH",
        "display" : "Mère"
      },
      {
        "code" : "MTHFOST",
        "display" : "Assistante familiale - Famille d'accueil"
      },
      {
        "code" : "MTHINLAW",
        "display" : "Belle-mère"
      },
      {
        "code" : "MUNCLE",
        "display" : "Oncle maternel"
      },
      {
        "code" : "NBOR",
        "display" : "Voisin(e)"
      },
      {
        "code" : "NBRO",
        "display" : "Frère biologique"
      },
      {
        "code" : "NCHILD",
        "display" : "Enfant biologique"
      },
      {
        "code" : "NEPHEW",
        "display" : "Neveu"
      },
      {
        "code" : "NFTH",
        "display" : "Père biologique"
      },
      {
        "code" : "NFTHF",
        "display" : "Père biologique du fœtus"
      },
      {
        "code" : "NIECE",
        "display" : "Nièce"
      },
      {
        "code" : "NIENEPH",
        "display" : "Neveu ou nièce"
      },
      {
        "code" : "NMTH",
        "display" : "Mère biologique"
      },
      {
        "code" : "NMTHF",
        "display" : "Mère biologique du fœtus"
      },
      {
        "code" : "NPRN",
        "display" : "Parent biologique, au sens père ou mère"
      },
      {
        "code" : "NSIB",
        "display" : "Frère ou soeur biologique"
      },
      {
        "code" : "NSIS",
        "display" : "Soeur biologique"
      },
      {
        "code" : "PAUNT",
        "display" : "Tante paternelle"
      },
      {
        "code" : "PCOUSN",
        "display" : "Cousin (paternel)"
      },
      {
        "code" : "PGGRFTH",
        "display" : "Arrière-grand-père paternel"
      },
      {
        "code" : "PGGRMTH",
        "display" : "Arrière-grand-mère paternelle"
      },
      {
        "code" : "PGGRPRN",
        "display" : "Arrière grand parent paternel"
      },
      {
        "code" : "PGRFTH",
        "display" : "Grand-père paternel"
      },
      {
        "code" : "PGRMTH",
        "display" : "Grand-mère paternelle"
      },
      {
        "code" : "PGRPRN",
        "display" : "Grand parent paternel"
      },
      {
        "code" : "PRN",
        "display" : "Parent, au sens père ou mère"
      },
      {
        "code" : "PRNINLAW",
        "display" : "Beau-père ou belle-mère"
      },
      {
        "code" : "PRNFOST",
        "display" : "Parent, au sens famille d'accueil"
      },
      {
        "code" : "PUNCLE",
        "display" : "Oncle paternel"
      },
      {
        "code" : "RESPRSN",
        "display" : "Responsable légal"
      },
      {
        "code" : "ROOM",
        "display" : "Personne vivant sous le même toit"
      },
      {
        "code" : "SIB",
        "display" : "Frère ou sœur"
      },
      {
        "code" : "SIBINLAW",
        "display" : "Beau-frère ou belle-sœur"
      },
      {
        "code" : "SIGOTHR",
        "display" : "Conjoint"
      },
      {
        "code" : "SIS",
        "display" : "Sœur"
      },
      {
        "code" : "SISINLAW",
        "display" : "Belle-sœur"
      },
      {
        "code" : "SON",
        "display" : "Fils biologique"
      },
      {
        "code" : "SONADOPT",
        "display" : "Fils adoptif"
      },
      {
        "code" : "SONC",
        "display" : "Fils"
      },
      {
        "code" : "SONFOST",
        "display" : "Garçon placé en famille d'accueil"
      },
      {
        "code" : "SONINLAW",
        "display" : "Gendre"
      },
      {
        "code" : "SPS",
        "display" : "Epoux ou épouse"
      },
      {
        "code" : "STPBRO",
        "display" : "Fils du beau-père ou de la belle-mère"
      },
      {
        "code" : "STPFTH",
        "display" : "Beau-père - époux du père ou de la mère"
      },
      {
        "code" : "STPMTH",
        "display" : "Belle-mère - épouse du père ou de la mère"
      },
      {
        "code" : "STPCHLD",
        "display" : "Enfant du conjoint, issu d'un mariage précédent"
      },
      {
        "code" : "STPDAU",
        "display" : "Fille du conjoint, issue d'un mariage précédent"
      },
      {
        "code" : "STPPRN",
        "display" : "Beau-père ou belle-mère - époux(se) du père ou de la mère"
      },
      {
        "code" : "STPSIB",
        "display" : "Enfant du beau-père ou de la belle-mère"
      },
      {
        "code" : "STPSIS",
        "display" : "Fille du beau-père ou de la belle-mère"
      },
      {
        "code" : "STPSON",
        "display" : "Fils du conjoint, issu d'un mariage précédent"
      },
      {
        "code" : "TWIN",
        "display" : "Frère jumeau ou soeur jumelle"
      },
      {
        "code" : "TWINBRO",
        "display" : "Frère jumeau"
      },
      {
        "code" : "TWINSIS",
        "display" : "Soeur jumelle"
      },
      {
        "code" : "UNCLE",
        "display" : "Oncle"
      },
      {
        "code" : "WIFE",
        "display" : "Epouse"
      }]
    }]
  }
}