{
  "resourceType" : "ValueSet",
  "id" : "804ab973-c32d-4289-9fad-27f2082b67ed-2526",
  "url" : "http://hl7.org/fhir/comparison/ValueSet/804ab973-c32d-4289-9fad-27f2082b67ed-2526",
  "name" : "IntersectionJdvRencontreCs9Cs24CisisAndJdvRencontreCs9Cs24Cisis",
  "title" : "Intersection of JDV Rencontre Cs9 Cs24 CISIS And JDV Rencontre Cs9 Cs24 CISIS",
  "status" : "active",
  "date" : "2025-09-18T11:10:17+00:00",
  "compose" : {
    "include" : [{
      "concept" : [{
        "code" : "ORG-196",
        "display" : "Lien avec le médecin de PMI après accord des parents"
      },
      {
        "code" : "ORG-194",
        "display" : "Orientation vers un autre professionnel de santé"
      },
      {
        "code" : "ORG-195",
        "display" : "Orientation vers une structure pluridisciplinaire (CAMPS centre de référence, réseau…)"
      }]
    }]
  }
}