{
  "resourceType" : "ValueSet",
  "id" : "804ab973-c32d-4289-9fad-27f2082b67ed-1773",
  "url" : "http://hl7.org/fhir/comparison/ValueSet/804ab973-c32d-4289-9fad-27f2082b67ed-1773",
  "name" : "IntersectionJdvCompletudeDispensationCisisAndJdvCompletudeDispensationCisis",
  "title" : "Intersection of JDV Completude Dispensation CISIS And JDV Completude Dispensation CISIS",
  "status" : "active",
  "date" : "2025-09-18T11:10:17+00:00",
  "compose" : {
    "include" : [{
      "concept" : [{
        "code" : "FFC",
        "display" : "Première dispensation - complète"
      },
      {
        "code" : "FFP",
        "display" : "Première dispensation - partielle"
      },
      {
        "code" : "RFP",
        "display" : "Dispensation suivante - partielle"
      },
      {
        "code" : "RFC",
        "display" : "Dispensation suivante - complète"
      }]
    }]
  }
}