{
  "resourceType" : "ValueSet",
  "id" : "804ab973-c32d-4289-9fad-27f2082b67ed-1016",
  "url" : "http://hl7.org/fhir/comparison/ValueSet/804ab973-c32d-4289-9fad-27f2082b67ed-1016",
  "name" : "UnionJDV_J154_TypeGlucose_ENSAndJDV_J154_TypeGlucose_ENS",
  "title" : "Union of null And null",
  "status" : "active",
  "date" : "2025-09-18T11:10:16+00:00",
  "jurisdiction" : [{
    "coding" : [{
      "system" : "urn:iso:std:iso:3166",
      "code" : "FR"
    }]
  }],
  "compose" : {
    "include" : [{
      "concept" : [{
        "code" : "2345-7",
        "display" : "Glucose [Masse/Volume] Sérum/Plasma ; Numérique"
      },
      {
        "code" : "4548-4",
        "display" : "Hémoglobine A1c/hémoglobine totale [Fraction massique] Sang ; Numérique"
      },
      {
        "code" : "99504-3",
        "display" : "Glucose [Masse/Volume] Liquide interstitiel ; Numérique"
      }]
    },
    {
      "concept" : [{
        "code" : "MED-972",
        "display" : "Index de gestion de glycémie (IGG)"
      }]
    }]
  }
}