{
  "resourceType" : "ValueSet",
  "id" : "08631b6e-9a42-4814-9df9-beb43bf8a22b-2205",
  "url" : "http://hl7.org/fhir/comparison/ValueSet/08631b6e-9a42-4814-9df9-beb43bf8a22b-2205",
  "name" : "IntersectionJdvLieuAccouchementCisisAndJdvLieuAccouchementCisis",
  "title" : "Intersection of JDV Lieu Accouchement CISIS And JDV Lieu Accouchement CISIS",
  "status" : "active",
  "date" : "2025-09-18T06:38:11+00:00",
  "compose" : {
    "include" : [{
      "concept" : [{
        "code" : "GEN-310",
        "display" : "Maternité"
      },
      {
        "code" : "GEN-092.06.04",
        "display" : "Autre lieu d'accouchement"
      }]
    },
    {
      "concept" : [{
        "code" : "169813005",
        "display" : "naissance à domicile"
      }]
    }]
  }
}