{
  "resourceType" : "ValueSet",
  "id" : "08631b6e-9a42-4814-9df9-beb43bf8a22b-2280",
  "url" : "http://hl7.org/fhir/comparison/ValueSet/08631b6e-9a42-4814-9df9-beb43bf8a22b-2280",
  "name" : "IntersectionJdvModaliteSortieCisisAndJdvModaliteSortieCisis",
  "title" : "Intersection of JDV Modalite Sortie CISIS And JDV Modalite Sortie CISIS",
  "status" : "active",
  "date" : "2025-09-18T06:38:11+00:00",
  "compose" : {
    "include" : [{
      "concept" : [{
        "code" : "GEN-092.06.01",
        "display" : "Autre établissement de santé"
      },
      {
        "code" : "GEN-092.06.03",
        "display" : "Autre destination"
      }]
    },
    {
      "concept" : [{
        "code" : "109",
        "display" : "Etablissement de santé privé autorisé en SSR"
      },
      {
        "code" : "127",
        "display" : "Hospitalisation à Domicile"
      },
      {
        "code" : "500",
        "display" : "Etablissement d'hébergement pour personnes âgées dépendantes"
      }]
    },
    {
      "concept" : [{
        "code" : "160849004",
        "display" : "retour au domicile"
      }]
    }]
  }
}