{
  "resourceType" : "ValueSet",
  "id" : "b87dbbe9-7d7a-4587-90dd-e1c04408c4b7-1968",
  "url" : "http://hl7.org/fhir/comparison/ValueSet/b87dbbe9-7d7a-4587-90dd-e1c04408c4b7-1968",
  "name" : "IntersectionJdvGestionEffetSecondaireCisisAndJdvGestionEffetSecondaireCisis",
  "title" : "Intersection of JDV Gestion Effet Secondaire CISIS And JDV Gestion Effet Secondaire CISIS",
  "status" : "active",
  "date" : "2025-06-26T13:09:32+00:00",
  "jurisdiction" : [{
    "coding" : [{
      "system" : "urn:iso:std:iso:3166",
      "code" : "FR"
    }]
  }],
  "compose" : {
    "include" : [{
      "concept" : [{
        "code" : "C20427",
        "display" : "facteur de croissance hématopoïétique"
      }]
    },
    {
      "concept" : [{
        "code" : "GEN-092.04.12",
        "display" : "Autre gestion des effets secondaires"
      }]
    }]
  }
}