{
  "resourceType" : "ValueSet",
  "id" : "b74bd7d8-dcb7-4f93-a7ba-b867d22e3b41-1988",
  "url" : "http://hl7.org/fhir/comparison/ValueSet/b74bd7d8-dcb7-4f93-a7ba-b867d22e3b41-1988",
  "name" : "UnionJdvHemisphereProfondCisisAndJdvHemisphereProfondCisis",
  "title" : "Union of JDV Hemisphere Profond CISIS And JDV Hemisphere Profond CISIS",
  "status" : "active",
  "date" : "2025-06-23T15:02:06+00:00",
  "jurisdiction" : [{
    "coding" : [{
      "system" : "urn:iso:std:iso:3166",
      "code" : "FR"
    }]
  }],
  "compose" : {
    "include" : [{
      "concept" : [{
        "code" : "51728003",
        "display" : "fibre thalamocorticale de la capsule interne"
      },
      {
        "code" : "54728004",
        "display" : "portion lenticulaire du bras postérieur de la capsule interne"
      },
      {
        "code" : "35764002",
        "display" : "ventricule cérébral"
      },
      {
        "code" : "11000004",
        "display" : "noyau caudé"
      }]
    }]
  }
}