{
  "resourceType" : "ValueSet",
  "id" : "23a0d0ca-eacc-46f2-9caf-f7badd0408ac-2846",
  "url" : "http://hl7.org/fhir/comparison/ValueSet/23a0d0ca-eacc-46f2-9caf-f7badd0408ac-2846",
  "name" : "UnionJdvTypeMigraineCisisAndJdvTypeMigraineCisis",
  "title" : "Union of JDV Type Migraine CISIS And JDV Type Migraine CISIS",
  "status" : "active",
  "date" : "2025-06-30T14:27:10+00:00",
  "jurisdiction" : [{
    "coding" : [{
      "system" : "urn:iso:std:iso:3166",
      "code" : "FR"
    }]
  }],
  "compose" : {
    "include" : [{
      "concept" : [{
        "code" : "G43.1",
        "display" : "Migraine avec aura [migraine classique]"
      },
      {
        "code" : "G43.0",
        "display" : "Migraine sans aura [migraine commune]"
      }]
    }]
  }
}