{
  "resourceType" : "ValueSet",
  "id" : "24b8c1f8-0b19-4fa6-85e3-0ef911dc2599-2580",
  "url" : "http://hl7.org/fhir/comparison/ValueSet/24b8c1f8-0b19-4fa6-85e3-0ef911dc2599-2580",
  "name" : "IntersectionJdvScoreBradenMobiliteCisisAndJdvScoreBradenMobiliteCisis",
  "title" : "Intersection of JDV Score Braden Mobilite CISIS And JDV Score Braden Mobilite CISIS",
  "status" : "active",
  "date" : "2025-06-27T11:37:37+00:00",
  "jurisdiction" : [{
    "coding" : [{
      "system" : "urn:iso:std:iso:3166",
      "code" : "FR"
    }]
  }],
  "compose" : {
    "include" : [{
      "concept" : [{
        "code" : "LA9614-4",
        "display" : "Complètement immobile"
      },
      {
        "code" : "LA9604-5",
        "display" : "Très limitée"
      },
      {
        "code" : "LA9605-2",
        "display" : "Légèrement limitée"
      },
      {
        "code" : "LA120-8",
        "display" : "Aucune limitation"
      }]
    }]
  }
}