{
  "resourceType" : "ValueSet",
  "id" : "b87dbbe9-7d7a-4587-90dd-e1c04408c4b7-2558",
  "url" : "http://hl7.org/fhir/comparison/ValueSet/b87dbbe9-7d7a-4587-90dd-e1c04408c4b7-2558",
  "name" : "UnionJdvRoleInformateurCisisAndJdvRoleInformateurCisis",
  "title" : "Union of Jdv Role Informateur CISIS And Jdv Role Informateur CISIS",
  "status" : "active",
  "date" : "2025-06-26T13:09:32+00:00",
  "jurisdiction" : [{
    "coding" : [{
      "system" : "urn:iso:std:iso:3166",
      "code" : "FR"
    }]
  }],
  "compose" : {
    "include" : [{
      "concept" : [{
        "code" : "CAREGIVER",
        "display" : "aidant"
      },
      {
        "code" : "CON",
        "display" : "informateur"
      },
      {
        "code" : "ECON",
        "display" : "personne à prévenir en cas d’urgence"
      },
      {
        "code" : "NOK",
        "display" : "personne de confiance"
      },
      {
        "code" : "PAT",
        "display" : "aidé"
      }]
    }]
  }
}