{
  "resourceType" : "ValueSet",
  "id" : "99f8fa72-8e71-43f7-a72a-fcbc89f94709-1950",
  "url" : "http://hl7.org/fhir/comparison/ValueSet/99f8fa72-8e71-43f7-a72a-fcbc89f94709-1950",
  "name" : "IntersectionJdvExamenRealiseCisisAndJdvExamenRealiseCisis",
  "title" : "Intersection of JDV Examen Realise CISIS And JDV Examen Realise CISIS",
  "status" : "active",
  "date" : "2025-09-30T04:26:49+00:00",
  "jurisdiction" : [{
    "coding" : [{
      "system" : "urn:iso:std:iso:3166",
      "code" : "FR"
    }]
  }],
  "compose" : {
    "include" : [{
      "concept" : [{
        "code" : "MED-034",
        "display" : "Agrandissement"
      }]
    },
    {
      "concept" : [{
        "code" : "387736007",
        "display" : "ponction à l'aiguille fine du sein"
      },
      {
        "code" : "16310003",
        "display" : "échographie"
      }]
    }]
  }
}