{
  "resourceType" : "ValueSet",
  "id" : "37f8c1a4-9e64-44f5-b71c-219cb28e90e7-2042",
  "url" : "http://hl7.org/fhir/comparison/ValueSet/37f8c1a4-9e64-44f5-b71c-219cb28e90e7-2042",
  "name" : "UnionActStatusAndActStatus",
  "title" : "Union of ActStatus And ActStatus",
  "status" : "active",
  "date" : "2025-10-01T10:17:13+00:00",
  "jurisdiction" : [{
    "coding" : [{
      "system" : "urn:iso:std:iso:3166",
      "code" : "FR"
    }]
  }],
  "compose" : {
    "include" : [{
      "concept" : [{
        "code" : "aborted",
        "display" : "Arrêté (après son lancement)"
      },
      {
        "code" : "active",
        "display" : "Actif (en cours ou à venir)"
      },
      {
        "code" : "cancelled",
        "display" : "Annulé (avant son lancement)"
      },
      {
        "code" : "completed",
        "display" : "Terminé"
      },
      {
        "code" : "held",
        "display" : "En attente (avant son lancement)"
      },
      {
        "code" : "new",
        "display" : "En préparation"
      },
      {
        "code" : "suspended",
        "display" : "Suspendu (au cours de sa réalisation)"
      }]
    }]
  }
}