{
  "resourceType" : "ValueSet",
  "id" : "37f8c1a4-9e64-44f5-b71c-219cb28e90e7-1427",
  "url" : "http://hl7.org/fhir/comparison/ValueSet/37f8c1a4-9e64-44f5-b71c-219cb28e90e7-1427",
  "name" : "UnionJDV_J39_ConditionTarifaire_RORAndJDV_J39_ConditionTarifaire_ROR",
  "title" : "Union of null And null",
  "status" : "active",
  "date" : "2025-10-01T10:17:13+00:00",
  "jurisdiction" : [{
    "coding" : [{
      "system" : "urn:iso:std:iso:3166",
      "code" : "FR"
    }]
  }],
  "compose" : {
    "include" : [{
      "concept" : [{
        "code" : "01",
        "display" : "Tarif public"
      },
      {
        "code" : "02",
        "display" : "Tarif agréé Aide Sociale"
      },
      {
        "code" : "03",
        "display" : "Tarif agréé ASH"
      }]
    }]
  }
}