{
  "resourceType" : "ValueSet",
  "id" : "99f8fa72-8e71-43f7-a72a-fcbc89f94709-2304",
  "url" : "http://hl7.org/fhir/comparison/ValueSet/99f8fa72-8e71-43f7-a72a-fcbc89f94709-2304",
  "name" : "IntersectionJdvModeSortieObpSemCisisAndJdvModeSortieObpSemCisis",
  "title" : "Intersection of JDV Mode Sortie Obp Sem CISIS And JDV Mode Sortie Obp Sem CISIS",
  "status" : "active",
  "date" : "2025-09-30T04:26:49+00:00",
  "jurisdiction" : [{
    "coding" : [{
      "system" : "urn:iso:std:iso:3166",
      "code" : "FR"
    }]
  }],
  "compose" : {
    "include" : [{
      "concept" : [{
        "code" : "GEN-302",
        "display" : "Avec sa mère"
      },
      {
        "code" : "GEN-092.06.09",
        "display" : "Autre mode de sortie"
      }]
    },
    {
      "concept" : [{
        "code" : "419620001",
        "display" : "mort"
      },
      {
        "code" : "107724000",
        "display" : "transfert du patient"
      }]
    }]
  }
}