{
  "resourceType" : "CodeSystem",
  "id" : "7d9c15a8-7c42-4b94-a6ca-28253f41dcc9-117",
  "url" : "http://hl7.org/fhir/comparison/CodeSystem/7d9c15a8-7c42-4b94-a6ca-28253f41dcc9-117",
  "name" : "IntersectionTRE_R06_SectionTableauCNOPAndTRE_R06_SectionTableauCNOP",
  "title" : "Intersection of null And null",
  "status" : "active",
  "date" : "2025-11-20T16:10:29+00:00",
  "property" : [{
    "code" : "dateValid",
    "description" : "date de validité d'un code concept",
    "type" : "dateTime"
  },
  {
    "code" : "dateMaj",
    "description" : "Date de mise à jour d'un code concept",
    "type" : "dateTime"
  },
  {
    "code" : "dateFin",
    "description" : "Date de fin d'exploitation d'un code concept",
    "type" : "dateTime"
  },
  {
    "code" : "deprecationDate",
    "uri" : "http://hl7.org/fhir/concept-properties#deprecationDate",
    "description" : "Date Concept was deprecated",
    "type" : "dateTime"
  },
  {
    "code" : "status",
    "uri" : "http://hl7.org/fhir/concept-properties#status",
    "description" : "A property that indicates the status of the concept.",
    "type" : "code"
  },
  {
    "code" : "retirementDate",
    "uri" : "http://hl7.org/fhir/concept-properties#retirementDate",
    "description" : "Date Concept was retired",
    "type" : "dateTime"
  },
  {
    "code" : "dateValid",
    "description" : "date de validité d'un code concept",
    "type" : "dateTime"
  },
  {
    "code" : "dateMaj",
    "description" : "Date de mise à jour d'un code concept",
    "type" : "dateTime"
  },
  {
    "code" : "dateFin",
    "description" : "Date de fin d'exploitation d'un code concept",
    "type" : "dateTime"
  },
  {
    "code" : "deprecationDate",
    "uri" : "http://hl7.org/fhir/concept-properties#deprecationDate",
    "description" : "Date Concept was deprecated",
    "type" : "dateTime"
  },
  {
    "code" : "status",
    "uri" : "http://hl7.org/fhir/concept-properties#status",
    "description" : "A property that indicates the status of the concept.",
    "type" : "code"
  },
  {
    "code" : "retirementDate",
    "uri" : "http://hl7.org/fhir/concept-properties#retirementDate",
    "description" : "Date Concept was retired",
    "type" : "dateTime"
  }],
  "concept" : [{
    "code" : "A",
    "display" : "Pharmacien titulaire d'officine",
    "designation" : [{
      "language" : "fr-FR",
      "use" : {
        "system" : "http://snomed.info/sct",
        "code" : "900000000000013009"
      },
      "value" : "Pharmacien titulaire officine"
    }],
    "property" : [{
      "code" : "dateValid",
      "valueDateTime" : "2007-07-25T15:04:42+01:00"
    },
    {
      "code" : "dateMaj",
      "valueDateTime" : "2016-09-01T00:00:00+01:00"
    },
    {
      "code" : "status",
      "valueCode" : "active"
    },
    {
      "code" : "dateValid",
      "valueDateTime" : "2007-07-25T15:04:42+01:00"
    },
    {
      "code" : "dateMaj",
      "valueDateTime" : "2016-09-01T00:00:00+01:00"
    },
    {
      "code" : "status",
      "valueCode" : "active"
    }]
  },
  {
    "code" : "B",
    "display" : "Pharmacien d'entreprise - industrie",
    "designation" : [{
      "language" : "fr-FR",
      "use" : {
        "system" : "http://snomed.info/sct",
        "code" : "900000000000013009"
      },
      "value" : "Pharmacien entreprise, indus"
    }],
    "property" : [{
      "code" : "dateValid",
      "valueDateTime" : "2007-07-25T15:04:42+01:00"
    },
    {
      "code" : "dateMaj",
      "valueDateTime" : "2016-09-01T00:00:00+01:00"
    },
    {
      "code" : "status",
      "valueCode" : "active"
    },
    {
      "code" : "dateValid",
      "valueDateTime" : "2007-07-25T15:04:42+01:00"
    },
    {
      "code" : "dateMaj",
      "valueDateTime" : "2016-09-01T00:00:00+01:00"
    },
    {
      "code" : "status",
      "valueCode" : "active"
    }]
  },
  {
    "code" : "C",
    "display" : "Pharmacien d'entreprise - distribution",
    "designation" : [{
      "language" : "fr-FR",
      "use" : {
        "system" : "http://snomed.info/sct",
        "code" : "900000000000013009"
      },
      "value" : "Pharmacien entreprise, distrib"
    }],
    "property" : [{
      "code" : "dateValid",
      "valueDateTime" : "2007-07-25T15:04:42+01:00"
    },
    {
      "code" : "dateMaj",
      "valueDateTime" : "2016-09-01T00:00:00+01:00"
    },
    {
      "code" : "status",
      "valueCode" : "active"
    },
    {
      "code" : "dateValid",
      "valueDateTime" : "2007-07-25T15:04:42+01:00"
    },
    {
      "code" : "dateMaj",
      "valueDateTime" : "2016-09-01T00:00:00+01:00"
    },
    {
      "code" : "status",
      "valueCode" : "active"
    }]
  },
  {
    "code" : "D",
    "display" : "Pharmacien adjoint, remplaçant ou gérant",
    "designation" : [{
      "language" : "fr-FR",
      "use" : {
        "system" : "http://snomed.info/sct",
        "code" : "900000000000013009"
      },
      "value" : "Pharmacien adjoint, divers"
    }],
    "property" : [{
      "code" : "dateValid",
      "valueDateTime" : "2007-07-25T15:04:42+01:00"
    },
    {
      "code" : "dateMaj",
      "valueDateTime" : "2016-09-01T00:00:00+01:00"
    },
    {
      "code" : "status",
      "valueCode" : "active"
    },
    {
      "code" : "dateValid",
      "valueDateTime" : "2007-07-25T15:04:42+01:00"
    },
    {
      "code" : "dateMaj",
      "valueDateTime" : "2016-09-01T00:00:00+01:00"
    },
    {
      "code" : "status",
      "valueCode" : "active"
    }]
  },
  {
    "code" : "E",
    "display" : "Pharmacien d'Outre-Mer",
    "property" : [{
      "code" : "dateValid",
      "valueDateTime" : "2007-07-25T15:04:42+01:00"
    },
    {
      "code" : "dateMaj",
      "valueDateTime" : "2016-09-01T00:00:00+01:00"
    },
    {
      "code" : "status",
      "valueCode" : "active"
    },
    {
      "code" : "dateValid",
      "valueDateTime" : "2007-07-25T15:04:42+01:00"
    },
    {
      "code" : "dateMaj",
      "valueDateTime" : "2016-09-01T00:00:00+01:00"
    },
    {
      "code" : "status",
      "valueCode" : "active"
    }]
  },
  {
    "code" : "G",
    "display" : "Pharmacien biologiste",
    "property" : [{
      "code" : "dateValid",
      "valueDateTime" : "2007-07-25T15:04:42+01:00"
    },
    {
      "code" : "dateMaj",
      "valueDateTime" : "2016-09-01T00:00:00+01:00"
    },
    {
      "code" : "status",
      "valueCode" : "active"
    },
    {
      "code" : "dateValid",
      "valueDateTime" : "2007-07-25T15:04:42+01:00"
    },
    {
      "code" : "dateMaj",
      "valueDateTime" : "2016-09-01T00:00:00+01:00"
    },
    {
      "code" : "status",
      "valueCode" : "active"
    }]
  },
  {
    "code" : "H",
    "display" : "Pharmacien d'établissement de santé",
    "designation" : [{
      "language" : "fr-FR",
      "use" : {
        "system" : "http://snomed.info/sct",
        "code" : "900000000000013009"
      },
      "value" : "Pharmacien d'étab de santé"
    }],
    "property" : [{
      "code" : "dateValid",
      "valueDateTime" : "2007-07-25T15:04:42+01:00"
    },
    {
      "code" : "dateMaj",
      "valueDateTime" : "2016-09-01T00:00:00+01:00"
    },
    {
      "code" : "status",
      "valueCode" : "active"
    },
    {
      "code" : "dateValid",
      "valueDateTime" : "2007-07-25T15:04:42+01:00"
    },
    {
      "code" : "dateMaj",
      "valueDateTime" : "2016-09-01T00:00:00+01:00"
    },
    {
      "code" : "status",
      "valueCode" : "active"
    }]
  },
  {
    "code" : "M",
    "display" : "Pharmacien militaire",
    "property" : [{
      "code" : "dateValid",
      "valueDateTime" : "2007-07-25T00:00:00+01:00"
    },
    {
      "code" : "dateMaj",
      "valueDateTime" : "2016-09-01T00:00:00+01:00"
    },
    {
      "code" : "status",
      "valueCode" : "active"
    },
    {
      "code" : "dateValid",
      "valueDateTime" : "2007-07-25T00:00:00+01:00"
    },
    {
      "code" : "dateMaj",
      "valueDateTime" : "2016-09-01T00:00:00+01:00"
    },
    {
      "code" : "status",
      "valueCode" : "active"
    }]
  }]
}