{
  "resourceType" : "ValueSet",
  "id" : "7d9c15a8-7c42-4b94-a6ca-28253f41dcc9-2630",
  "url" : "http://hl7.org/fhir/comparison/ValueSet/7d9c15a8-7c42-4b94-a6ca-28253f41dcc9-2630",
  "name" : "UnionJdvScoreDukeCisisAndJdvScoreDukeCisis",
  "title" : "Union of JDV Score Duke CISIS And JDV Score Duke CISIS",
  "status" : "active",
  "date" : "2025-11-20T16:10:30+00:00",
  "jurisdiction" : [{
    "coding" : [{
      "system" : "urn:iso:std:iso:3166",
      "code" : "FRA"
    }]
  }],
  "compose" : {
    "include" : [{
      "concept" : [{
        "code" : "MED-589",
        "display" : "Aptitude physique excellente (Score de Duke > 10 MET)"
      },
      {
        "code" : "MED-590",
        "display" : "Aptitude physique bonne (Score de Duke 7-10 MET)"
      },
      {
        "code" : "MED-591",
        "display" : "Aptitude physique modérée (Score de Duke 4-7 MET)"
      },
      {
        "code" : "MED-592",
        "display" : "Aptitude physique faible (Score de Duke < 4 MET)"
      }]
    }]
  }
}