{
  "resourceType" : "ValueSet",
  "id" : "5d1b9a2d-3428-4aab-b434-63315f5a7e1e-1535",
  "url" : "http://hl7.org/fhir/comparison/ValueSet/5d1b9a2d-3428-4aab-b434-63315f5a7e1e-1535",
  "name" : "UnionJDV_J86_NatCycleForm_RASSAndJDV_J86_NatCycleForm_RASS",
  "title" : "Union of null And null",
  "status" : "active",
  "date" : "2025-06-04T08:10:46+00:00",
  "compose" : {
    "include" : [{
      "concept" : [{
        "code" : "C2",
        "display" : "2ième cycle"
      },
      {
        "code" : "C3C",
        "display" : "3ième cycle court"
      },
      {
        "code" : "C3L",
        "display" : "3ième cycle long / internat"
      }]
    }]
  }
}