{
  "resourceType" : "ValueSet",
  "id" : "c3ec7e94-82a3-44b3-ab7d-a88d03688050-1244",
  "url" : "http://hl7.org/fhir/comparison/ValueSet/c3ec7e94-82a3-44b3-ab7d-a88d03688050-1244",
  "name" : "UnionJDV_J233_TypeDiplome_EPARSAndJDV_J233_TypeDiplome_EPARS",
  "title" : "Union of null And null",
  "status" : "active",
  "date" : "2025-06-03T16:20:34+00:00",
  "compose" : {
    "include" : [{
      "concept" : [{
        "code" : "DE",
        "display" : "Diplôme d'Etat français"
      },
      {
        "code" : "AU",
        "display" : "Autre type de diplôme"
      },
      {
        "code" : "DU",
        "display" : "Diplôme d'université (DU) ou inter-universitaire (DIU)"
      },
      {
        "code" : "ATT",
        "display" : "Attestation"
      }]
    }]
  }
}