<?xml version="1.0" encoding="UTF-8"?>
<RetrieveValueSetResponse xmlns="urn:ihe:iti:svs:2008"
                          xmlns:xsi="http://www.w3.org/2001/XMLSchema-instance">
   <ValueSet dateFin=""
             dateMaj="20260619134042"
             dateValid="20240905000000"
             description="ActMood"
             displayName="ActMood"
             id="2.16.840.1.113883.1.11.10196"
             typeFichier="JDV"
             urlFichier="">
      <ConceptList>
         <Concept code="DEF"
                  codeSystem="2.16.840.1.113883.5.1001"
                  displayName="Définition"/>
         <Concept code="PERM"
                  codeSystem="2.16.840.1.113883.5.1001"
                  displayName="Permission"/>
         <Concept code="SLOT"
                  codeSystem="2.16.840.1.113883.5.1001"
                  displayName="Possible sur la période spécifiée"/>
         <Concept code="EVN"
                  codeSystem="2.16.840.1.113883.5.1001"
                  displayName="Réalisé"/>
         <Concept code="INT"
                  codeSystem="2.16.840.1.113883.5.1001"
                  displayName="Prévu"/>
         <Concept code="ARQ"
                  codeSystem="2.16.840.1.113883.5.1001"
                  displayName="Prévu mais non confirmé"/>
         <Concept code="PERMRQ"
                  codeSystem="2.16.840.1.113883.5.1001"
                  displayName="Demande d'autorisation"/>
         <Concept code="RQO"
                  codeSystem="2.16.840.1.113883.5.1001"
                  displayName="Demande"/>
         <Concept code="PRP"
                  codeSystem="2.16.840.1.113883.5.1001"
                  displayName="Proposition"/>
         <Concept code="RMD"
                  codeSystem="2.16.840.1.113883.5.1001"
                  displayName="Recommandation"/>
         <Concept code="PRMS"
                  codeSystem="2.16.840.1.113883.5.1001"
                  displayName="Planifié et confirmé"/>
         <Concept code="APT"
                  codeSystem="2.16.840.1.113883.5.1001"
                  displayName="Date et lieu confirmé"/>
         <Concept code="EXPEC"
                  codeSystem="2.16.840.1.113883.5.1001"
                  displayName="Attendu"/>
         <Concept code="GOL" codeSystem="2.16.840.1.113883.5.1001" displayName="But"/>
         <Concept code="RSK"
                  codeSystem="2.16.840.1.113883.5.1001"
                  displayName="Risque"/>
         <Concept code="OPT"
                  codeSystem="2.16.840.1.113883.5.1001"
                  displayName="Option"/>
      </ConceptList>
   </ValueSet>
</RetrieveValueSetResponse>
