<?xml version="1.0" encoding="UTF-8"?>
<RetrieveValueSetResponse xmlns="urn:ihe:iti:svs:2008"
                          xmlns:xsi="http://www.w3.org/2001/XMLSchema-instance">
   <ValueSet dateFin=""
             dateMaj="20221231000000"
             dateValid="20210315000000"
             description="JDV_ClinicalStatusCodes_CISIS"
             displayName="JDV_ClinicalStatusCodes_CISIS"
             id="1.2.250.1.213.1.1.4.2.283.2"
             typeFichier="JDV"
             urlFichier="">
      <ConceptList>
         <Concept code="CDA_002" codeSystem="" displayName="Résolu"/>
         <Concept code="G-A201" codeSystem="" displayName="Exclus"/>
         <Concept code="G-A202" codeSystem="" displayName="Ecarté"/>
         <Concept code="G-A230" codeSystem="" displayName="Actif"/>
         <Concept code="G-A270" codeSystem="" displayName="Chronique"/>
         <Concept code="G-A378" codeSystem="" displayName="Inactif"/>
         <Concept code="G-A397" codeSystem="" displayName="Intermittent"/>
         <Concept code="G-A500" codeSystem="" displayName="Récurrent"/>
      </ConceptList>
   </ValueSet>
</RetrieveValueSetResponse>
