<?xml version="1.0" encoding="UTF-8"?>
<RetrieveValueSetResponse xmlns="urn:ihe:iti:svs:2008"
                          xmlns:xsi="http://www.w3.org/2001/XMLSchema-instance">
   <ValueSet dateFin=""
             dateMaj="20230404000000"
             dateValid="20210315000000"
             description="JDV_Pharynx_pN_carcinome_nasoPharynx_CISIS"
             displayName="JDV_Pharynx_pN_carcinome_nasoPharynx_CISIS"
             id="1.2.250.1.213.1.1.5.379"
             typeFichier="JDV"
             urlFichier="">
      <ConceptList>
         <Concept code="1626"
                  codeSystem=""
                  displayName="pN0: No regional lymph node metastasis"/>
         <Concept code="1627"
                  codeSystem=""
                  displayName="pN1: Unilateral metastasis in lymph node(s), 6 cm or less in greatest dimension, above the supraclavicular fossa"/>
         <Concept code="1628"
                  codeSystem=""
                  displayName="pN2: Bilateral metastasis in lymph node(s), 6 cm or less in greatest dimension, above the supraclavicular fossa"/>
         <Concept code="1629"
                  codeSystem=""
                  displayName="pN3: Metastasis in a lymph node greater than 6 cm and/or to supraclavicular fossa"/>
         <Concept code="1630"
                  codeSystem=""
                  displayName="pN3a: Greater than 6 cm in dimension"/>
         <Concept code="1631"
                  codeSystem=""
                  displayName="pN3b: Extension to the supraclavicular fossa"/>
      </ConceptList>
   </ValueSet>
</RetrieveValueSetResponse>
