{
  "resourceType" : "ValueSet",
  "id" : "6f747092-6ba1-46ce-9c36-120e03b840ab-1203",
  "url" : "http://hl7.org/fhir/comparison/ValueSet/6f747092-6ba1-46ce-9c36-120e03b840ab-1203",
  "name" : "IntersectionJDV_J218_CNAMAmeliSecteurConventionnement_RORAndJDV_J218_CNAMAmeliSecteurConventionnement_ROR",
  "title" : "Intersection of null And null",
  "status" : "active",
  "date" : "2025-06-11T12:46:02+00:00",
  "compose" : {
    "include" : [{
      "concept" : [{
        "code" : "nc",
        "display" : "Non conventionné"
      },
      {
        "code" : "c1",
        "display" : "Secteur 1 ou conventionné"
      },
      {
        "code" : "c2",
        "display" : "Secteur 1 ou conventionné avec droit au dépassement permanent"
      },
      {
        "code" : "c3",
        "display" : "Secteur 2"
      }]
    }]
  }
}