{
  "resourceType" : "ValueSet",
  "id" : "e767ae11-c55f-4088-8e5e-006807d85d45-2682",
  "url" : "http://hl7.org/fhir/comparison/ValueSet/e767ae11-c55f-4088-8e5e-006807d85d45-2682",
  "name" : "IntersectionJdvTnmPtnmPn1CisisAndJdvTnmPtnmPn1Cisis",
  "title" : "Intersection of JDV Tnm Ptnm Pn 1 CISIS And JDV Tnm Ptnm Pn 1 CISIS",
  "status" : "active",
  "date" : "2025-06-19T12:25:15+00:00",
  "compose" : {
    "include" : [{
      "concept" : [{
        "code" : "MED-795",
        "display" : "Ganglions  lymphatiques régionaux non évaluables"
      },
      {
        "code" : "MED-796",
        "display" : "Pas de métastase ganglionnaire lymphatique régionale"
      },
      {
        "code" : "MED-809",
        "display" : "Métastase(s) dans les ganglions lymphatiques régionaux"
      }]
    }]
  }
}