{
  "resourceType" : "ValueSet",
  "id" : "6db36f5d-dafa-4e4c-adfa-b6f861c86eed-1527",
  "url" : "http://hl7.org/fhir/comparison/ValueSet/6db36f5d-dafa-4e4c-adfa-b6f861c86eed-1527",
  "name" : "IntersectionJDV_J80_Sexe_RASSAndJDV_J80_Sexe_RASS",
  "title" : "Intersection of null And null",
  "status" : "active",
  "date" : "2025-06-18T10:30:55+00:00",
  "compose" : {
    "include" : [{
      "concept" : [{
        "code" : "UN",
        "display" : "Inconnu"
      },
      {
        "code" : "F",
        "display" : "Féminin"
      },
      {
        "code" : "M",
        "display" : "Masculin"
      },
      {
        "code" : "O",
        "display" : "Autre sexe (ni masculin, ni féminin)"
      }]
    }]
  }
}