{
  "resourceType" : "ValueSet",
  "id" : "03274c62-abd5-41df-91f4-62c6d76d88a6-1931",
  "url" : "http://hl7.org/fhir/comparison/ValueSet/03274c62-abd5-41df-91f4-62c6d76d88a6-1931",
  "name" : "UnionJdvFacteurDeRisqueProfessionnelCisisAndJdvFacteurDeRisqueProfessionnelCisis",
  "title" : "Union of JDV Facteur De Risque Professionnel CISIS And JDV Facteur De Risque Professionnel CISIS",
  "status" : "active",
  "date" : "2025-06-19T14:27:47+00:00",
  "jurisdiction" : [{
    "coding" : [{
      "system" : "urn:iso:std:iso:3166",
      "code" : "FR"
    }]
  }],
  "compose" : {
    "include" : [{
      "concept" : [{
        "code" : "83581005",
        "display" : "silice colloidale"
      },
      {
        "code" : "16369005",
        "display" : "Asbestos"
      },
      {
        "code" : "61010005",
        "display" : "solvant"
      },
      {
        "code" : "59545008",
        "display" : "pesticide"
      }]
    }]
  }
}