{
  "resourceType" : "ValueSet",
  "id" : "4c268131-8ba8-4807-bb1d-69cf9eb5e5e2-1986",
  "url" : "http://hl7.org/fhir/comparison/ValueSet/4c268131-8ba8-4807-bb1d-69cf9eb5e5e2-1986",
  "name" : "IntersectionAllergyIntoleranceClinicalStatusCodesAndAllergyIntoleranceClinicalStatusCodes",
  "title" : "Intersection of AllergyIntolerance Clinical Status Codes And AllergyIntolerance Clinical Status Codes",
  "status" : "active",
  "date" : "2025-06-19T11:40:36+00:00",
  "compose" : {
    "include" : [{
      "concept" : [{
        "code" : "active",
        "display" : "Actif"
      },
      {
        "code" : "inactive",
        "display" : "Inactif"
      },
      {
        "code" : "resolved",
        "display" : "Résolu"
      }]
    }]
  }
}