{
  "resourceType" : "ValueSet",
  "id" : "58ea2990-fa3c-4ab6-8cb3-d7118e1b8e9b-1617",
  "url" : "http://hl7.org/fhir/comparison/ValueSet/58ea2990-fa3c-4ab6-8cb3-d7118e1b8e9b-1617",
  "name" : "IntersectionJdvAccesArtereCisisAndJdvAccesArtereCisis",
  "title" : "Intersection of JDV Acces Artere CISIS And JDV Acces Artere CISIS",
  "status" : "active",
  "date" : "2025-06-16T15:42:16+00:00",
  "compose" : {
    "include" : [{
      "concept" : [{
        "code" : "244332003",
        "display" : "artère fémorale entière"
      },
      {
        "code" : "181332001",
        "display" : "artère radiale entière"
      }]
    }]
  }
}