{
  "resourceType" : "ValueSet",
  "id" : "4cd2faaa-145b-40ae-bc22-4d61a980e3fd-905",
  "url" : "http://hl7.org/fhir/comparison/ValueSet/4cd2faaa-145b-40ae-bc22-4d61a980e3fd-905",
  "name" : "UnionJDV_J124_CommuneAndJDV_J124_Commune",
  "title" : "Union of null And null",
  "status" : "active",
  "date" : "2025-06-12T14:18:26+00:00",
  "jurisdiction" : [{
    "coding" : [{
      "system" : "urn:iso:std:iso:3166",
      "code" : "FR"
    }]
  }],
  "compose" : {
    "include" : [{
      "filter" : [{
        "property" : "dateFin",
        "op" : "exists",
        "value" : "false"
      }]
    }]
  }
}