{
  "resourceType" : "ValueSet",
  "id" : "ff19805b-2d94-4a0b-8857-9cb880268fd3-969",
  "url" : "http://hl7.org/fhir/comparison/ValueSet/ff19805b-2d94-4a0b-8857-9cb880268fd3-969",
  "name" : "IntersectionJDV_J143_AdministrativeGender_CISISAndJDV_J143_AdministrativeGender_CISIS",
  "title" : "Intersection of null And null",
  "status" : "active",
  "date" : "2025-06-17T11:35:50+00:00",
  "compose" : {
    "include" : [{
      "concept" : [{
        "code" : "F",
        "display" : "Féminin"
      },
      {
        "code" : "M",
        "display" : "Masculin"
      },
      {
        "code" : "UN",
        "display" : "Inconnu"
      }]
    }]
  }
}