{
  "resourceType" : "ValueSet",
  "id" : "598d4790-8074-4426-8d0d-a79ff5296634-1334",
  "url" : "http://hl7.org/fhir/comparison/ValueSet/598d4790-8074-4426-8d0d-a79ff5296634-1334",
  "name" : "UnionJDV_J261_SourceInformationInstallation_RASSAndJDV_J261_SourceInformationInstallation_RASS",
  "title" : "Union of null And null",
  "status" : "active",
  "date" : "2025-06-11T14:49:30+00:00",
  "jurisdiction" : [{
    "coding" : [{
      "system" : "urn:iso:std:iso:3166",
      "code" : "FR"
    }]
  }],
  "compose" : {
    "include" : [{
      "concept" : [{
        "code" : "V",
        "display" : "Visite de conformité"
      },
      {
        "code" : "E",
        "display" : "Enquête statistique"
      },
      {
        "code" : "I",
        "display" : "Interrogation de l'ET"
      },
      {
        "code" : "D",
        "display" : "Document de tarification"
      },
      {
        "code" : "S",
        "display" : "Inspection"
      },
      {
        "code" : "C",
        "display" : "Convention"
      },
      {
        "code" : "L",
        "display" : "Labellisation"
      },
      {
        "code" : "A",
        "display" : "Autre"
      },
      {
        "code" : "R",
        "display" : "Arrêté"
      }]
    }]
  }
}