{
  "resourceType" : "ValueSet",
  "id" : "598d4790-8074-4426-8d0d-a79ff5296634-2543",
  "url" : "http://hl7.org/fhir/comparison/ValueSet/598d4790-8074-4426-8d0d-a79ff5296634-2543",
  "name" : "UnionJdvScoreAsaCisisAndJdvScoreAsaCisis",
  "title" : "Union of JDV Score Asa CISIS And JDV Score Asa CISIS",
  "status" : "active",
  "date" : "2025-06-11T14:49:30+00:00",
  "jurisdiction" : [{
    "coding" : [{
      "system" : "urn:iso:std:iso:3166",
      "code" : "FR"
    }]
  }],
  "compose" : {
    "include" : [{
      "concept" : [{
        "code" : "413495001",
        "display" : "classe I du système de classification de l'état physique de l'American Society of Anesthesiologists"
      },
      {
        "code" : "413496000",
        "display" : "classe II du système de classification de l'état physique de l'American Society of Anesthesiologists"
      },
      {
        "code" : "413497009",
        "display" : "classe III du système de classification de l'état physique de l'American Society of Anesthesiologists"
      },
      {
        "code" : "413498004",
        "display" : "classe IV du système de classification de l'état physique de l'American Society of Anesthesiologists"
      },
      {
        "code" : "413499007",
        "display" : "classe V du système de classification de l'état physique de l'American Society of Anesthesiologists"
      },
      {
        "code" : "413500003",
        "display" : "classe VI du système de classification de l'état physique de l'American Society of Anesthesiologists"
      }]
    }]
  }
}