{
  "resourceType" : "ValueSet",
  "id" : "e767ae11-c55f-4088-8e5e-006807d85d45-2469",
  "url" : "http://hl7.org/fhir/comparison/ValueSet/e767ae11-c55f-4088-8e5e-006807d85d45-2469",
  "name" : "IntersectionJdvRepriseProfessionnelleCisisAndJdvRepriseProfessionnelleCisis",
  "title" : "Intersection of JDV Reprise Professionnelle CISIS And JDV Reprise Professionnelle CISIS",
  "status" : "active",
  "date" : "2025-06-19T12:25:15+00:00",
  "compose" : {
    "include" : [{
      "concept" : [{
        "code" : "GEN-125",
        "display" : "Reprise à envisager. Démarches faites."
      },
      {
        "code" : "GEN-126",
        "display" : "Reprise inenvisageable. Démarches faites."
      }]
    }]
  }
}