{
  "resourceType" : "ValueSet",
  "id" : "6d7e7949-f883-4020-85b8-4f0301e9d270-2457",
  "url" : "http://hl7.org/fhir/comparison/ValueSet/6d7e7949-f883-4020-85b8-4f0301e9d270-2457",
  "name" : "IntersectionJdvPolypathologiesAvcCisisAndJdvPolypathologiesAvcCisis",
  "title" : "Intersection of JDV Polypathologies Avc CISIS And JDV Polypathologies Avc CISIS",
  "status" : "active",
  "date" : "2025-07-28T13:12:13+00:00",
  "jurisdiction" : [{
    "coding" : [{
      "system" : "urn:iso:std:iso:3166",
      "code" : "FR"
    }]
  }],
  "compose" : {
    "include" : [{
      "concept" : [{
        "code" : "MED-320",
        "display" : "Affection longue durée (ALD)"
      },
      {
        "code" : "MED-321",
        "display" : "Surhandicap"
      },
      {
        "code" : "MED-322",
        "display" : "Plurihandicap"
      },
      {
        "code" : "MED-323",
        "display" : "Polyhandicap"
      },
      {
        "code" : "MED-324",
        "display" : "Polypathologies"
      }]
    }]
  }
}