{
  "resourceType" : "ValueSet",
  "id" : "6d7e7949-f883-4020-85b8-4f0301e9d270-1062",
  "url" : "http://hl7.org/fhir/comparison/ValueSet/6d7e7949-f883-4020-85b8-4f0301e9d270-1062",
  "name" : "IntersectionJDV_J169_MotifFinActivite_EPARSAndJDV_J169_MotifFinActivite_EPARS",
  "title" : "Intersection of null And null",
  "status" : "active",
  "date" : "2025-07-28T13:12:13+00:00",
  "jurisdiction" : [{
    "coding" : [{
      "system" : "urn:iso:std:iso:3166",
      "code" : "FR"
    }]
  }],
  "compose" : {
    "include" : [{
      "concept" : [{
        "code" : "AUT",
        "display" : "Autre motif"
      },
      {
        "code" : "CHA",
        "display" : "Changement d'activité"
      },
      {
        "code" : "CHL",
        "display" : "Changement de lieu d'exercice"
      },
      {
        "code" : "CHP",
        "display" : "Changement de profession"
      },
      {
        "code" : "DCD",
        "display" : "Décès"
      },
      {
        "code" : "ETR",
        "display" : "Départ à l'étranger"
      },
      {
        "code" : "RH",
        "display" : "Retraite hospitalière"
      },
      {
        "code" : "RL",
        "display" : "Retraite libérale"
      },
      {
        "code" : "RS",
        "display" : "Retraite salariée"
      }]
    }]
  }
}