{
  "resourceType" : "ValueSet",
  "id" : "6e80de06-0bc2-4c3d-bd8e-7bceae418507-1932",
  "url" : "http://hl7.org/fhir/comparison/ValueSet/6e80de06-0bc2-4c3d-bd8e-7bceae418507-1932",
  "name" : "IntersectionJdvExamenCliniqueCisisAndJdvExamenCliniqueCisis",
  "title" : "Intersection of JDV Examen Clinique CISIS And JDV Examen Clinique CISIS",
  "status" : "active",
  "date" : "2025-07-25T10:43:22+00:00",
  "jurisdiction" : [{
    "coding" : [{
      "system" : "urn:iso:std:iso:3166",
      "code" : "FR"
    }]
  }],
  "compose" : {
    "include" : [{
      "concept" : [{
        "code" : "GEN-038",
        "display" : "Bénin"
      },
      {
        "code" : "GEN-103",
        "display" : "Normal"
      },
      {
        "code" : "GEN-011",
        "display" : "Refus"
      },
      {
        "code" : "GEN-039",
        "display" : "Suspect"
      },
      {
        "code" : "MED-117",
        "display" : "Asymétrie mammaire"
      }]
    }]
  }
}