{
  "resourceType" : "ValueSet",
  "id" : "abdcfdc2-2300-4d38-b9c1-97871a5eea5c-1728",
  "url" : "http://hl7.org/fhir/comparison/ValueSet/abdcfdc2-2300-4d38-b9c1-97871a5eea5c-1728",
  "name" : "IntersectionJdvCauseCesarienneCisisAndJdvCauseCesarienneCisis",
  "title" : "Intersection of JDV Cause Cesarienne CISIS And JDV Cause Cesarienne CISIS",
  "status" : "active",
  "date" : "2025-07-28T10:01:35+00:00",
  "compose" : {
    "include" : [{
      "concept" : [{
        "code" : "MED-219",
        "display" : "Cause maternelle"
      },
      {
        "code" : "MED-210",
        "display" : "Cause fœtale"
      },
      {
        "code" : "MED-1272",
        "display" : "Cause materno-fœtale"
      }]
    }]
  }
}