{
  "resourceType" : "ValueSet",
  "id" : "a21150dc-0ce2-4c3d-ba9c-5ec6ebbb8c1d-1611",
  "url" : "http://hl7.org/fhir/comparison/ValueSet/a21150dc-0ce2-4c3d-ba9c-5ec6ebbb8c1d-1611",
  "name" : "IntersectionJdvAbsentOrUnknownAllergyCisisAndJdvAbsentOrUnknownAllergyCisis",
  "title" : "Intersection of JDV Absent Or Unknown Allergy CISIS And JDV Absent Or Unknown Allergy CISIS",
  "status" : "active",
  "date" : "2025-07-18T07:57:59+00:00",
  "compose" : {
    "include" : [{
      "concept" : [{
        "code" : "no-allergy-info",
        "display" : "Pas d’information sur les allergies/hypersensibilités"
      },
      {
        "code" : "no-known-allergies",
        "display" : "Pas d'allergie/hypersensibilité connue"
      },
      {
        "code" : "no-known-medication-allergies",
        "display" : "Pas d'allergie médicamenteuse connue"
      },
      {
        "code" : "no-known-environmental-allergies",
        "display" : "Pas d'allergie environnementale connue"
      },
      {
        "code" : "no-known-food-allergies",
        "display" : "Pas d'allergie alimentaire connue"
      }]
    }]
  }
}