{
  "resourceType" : "ValueSet",
  "id" : "4a786e0e-102d-4938-a221-87a4054bdd27-2891",
  "url" : "http://hl7.org/fhir/comparison/ValueSet/4a786e0e-102d-4938-a221-87a4054bdd27-2891",
  "name" : "UnionJdvTypeIntubationCisisAndJdvTypeIntubationCisis",
  "title" : "Union of JDV Type Intubation CISIS And JDV Type Intubation CISIS",
  "status" : "active",
  "date" : "2025-07-17T14:32:10+00:00",
  "jurisdiction" : [{
    "coding" : [{
      "system" : "urn:iso:std:iso:3166",
      "code" : "FR"
    }]
  }],
  "compose" : {
    "include" : [{
      "concept" : [{
        "code" : "MED-657",
        "display" : "Abord trachéal direct"
      }]
    },
    {
      "concept" : [{
        "code" : "232674004",
        "display" : "intubation orotrachéale"
      },
      {
        "code" : "232679009",
        "display" : "intubation nasotrachéale"
      }]
    }]
  }
}