{
  "resourceType" : "ValueSet",
  "id" : "bb1913d6-42c5-40c9-a9bb-9750d1fdfd0e-1257",
  "url" : "http://hl7.org/fhir/comparison/ValueSet/bb1913d6-42c5-40c9-a9bb-9750d1fdfd0e-1257",
  "name" : "IntersectionJDV_J231_XdsTypesIdentifiantsReferenceId_DMPAndJDV_J231_XdsTypesIdentifiantsReferenceId_DMP",
  "title" : "Intersection of null And null",
  "status" : "active",
  "date" : "2025-07-16T12:49:54+00:00",
  "jurisdiction" : [{
    "coding" : [{
      "system" : "urn:iso:std:iso:3166",
      "code" : "FR"
    }]
  }],
  "compose" : {
    "include" : [{
      "concept" : [{
        "code" : "urn:ihe:iti:xds:2013:accession",
        "display" : "accession"
      },
      {
        "code" : "urn:ihe:iti:xds:2013:order",
        "display" : "order"
      },
      {
        "code" : "urn:ihe:iti:xds:2016:studyInstanceUID",
        "display" : "studyInstanceUID"
      }]
    }]
  }
}