{
  "resourceType" : "ValueSet",
  "id" : "a21150dc-0ce2-4c3d-ba9c-5ec6ebbb8c1d-2141",
  "url" : "http://hl7.org/fhir/comparison/ValueSet/a21150dc-0ce2-4c3d-ba9c-5ec6ebbb8c1d-2141",
  "name" : "UnionJdvInfoDecesCs8CisisAndJdvInfoDecesCs8Cisis",
  "title" : "Union of JDV Info Deces Cs8 CISIS And JDV Info Deces Cs8 CISIS",
  "status" : "active",
  "date" : "2025-07-18T07:57:59+00:00",
  "jurisdiction" : [{
    "coding" : [{
      "system" : "urn:iso:std:iso:3166",
      "code" : "FR"
    }]
  }],
  "compose" : {
    "include" : [{
      "concept" : [{
        "code" : "MED-173",
        "display" : "Mort de l'enfant"
      },
      {
        "code" : "PAT-034",
        "display" : "Age au moment du décès"
      }]
    },
    {
      "concept" : [{
        "code" : "79378-6",
        "display" : "Causes du décès"
      }]
    }]
  }
}