{
  "resourceType" : "ValueSet",
  "id" : "bb1913d6-42c5-40c9-a9bb-9750d1fdfd0e-2622",
  "url" : "http://hl7.org/fhir/comparison/ValueSet/bb1913d6-42c5-40c9-a9bb-9750d1fdfd0e-2622",
  "name" : "IntersectionJdvScoreBradenComponentCisisAndJdvScoreBradenComponentCisis",
  "title" : "Intersection of JDV Score Braden Component CISIS And JDV Score Braden Component CISIS",
  "status" : "active",
  "date" : "2025-07-16T12:49:54+00:00",
  "compose" : {
    "include" : [{
      "concept" : [{
        "code" : "38222-6",
        "display" : "Perception sensorielle"
      },
      {
        "code" : "38229-1",
        "display" : "Exposition à l'humidité"
      },
      {
        "code" : "38224-2",
        "display" : "Mobilité"
      },
      {
        "code" : "38223-4",
        "display" : "Activité"
      },
      {
        "code" : "38225-9",
        "display" : "Nutrition"
      },
      {
        "code" : "38226-7",
        "display" : "Friction et cisaillement"
      }]
    }]
  }
}